{
  "resourceType": "Patient",
  "id": "{{pat_id}}", // An identifier for this patient
  "active": false,
  "meta": [{
    "versionId": "1",
    "lastUpdated": "2018-11-12T10:19:25.176+00:00"
  }],
  "text": [{
    "status": "generated",
    "div": "<div xmlns=\"http://www.w3.org/1999/xhtml\"> </div>"
  }],

  "identifier": [
    {
      "value": "{{pat_id}}",
      "assigner": {
        "display": "Maastro"
      }
    }
  ],
  "gender" : "{{gender}}",
  "birthDate" : "{{birthDate}}",
  "deceasedBoolean" : "{{deceasedBoolean}}"
}

